LICENSE
MANIFEST.in
README.md
pyproject.toml
setup.py
vulkpy/__init__.py
vulkpy/_vkarray.cc
vulkpy/random.py
vulkpy/util.py
vulkpy/vkarray.py
vulkpy/vktyping.py
vulkpy.egg-info/PKG-INFO
vulkpy.egg-info/SOURCES.txt
vulkpy.egg-info/dependency_links.txt
vulkpy.egg-info/requires.txt
vulkpy.egg-info/top_level.txt
vulkpy/nn/__init__.py
vulkpy/nn/core.py
vulkpy/nn/initializers.py
vulkpy/nn/layers.py
vulkpy/nn/losses.py
vulkpy/nn/models.py
vulkpy/nn/optimizers.py
vulkpy/nn/parameters.py
vulkpy/nn/regularizers.py
vulkpy/shader/abs.spv
vulkpy/shader/acos.spv
vulkpy/shader/acosh.spv
vulkpy/shader/add.spv
vulkpy/shader/add_broadcast.spv
vulkpy/shader/add_scalar.spv
vulkpy/shader/asin.spv
vulkpy/shader/asinh.spv
vulkpy/shader/atan.spv
vulkpy/shader/atanh.spv
vulkpy/shader/batch_affine.spv
vulkpy/shader/broadcast.spv
vulkpy/shader/clamp.spv
vulkpy/shader/clamp_ss.spv
vulkpy/shader/clamp_sv.spv
vulkpy/shader/clamp_vs.spv
vulkpy/shader/cos.spv
vulkpy/shader/cosh.spv
vulkpy/shader/div.spv
vulkpy/shader/div_broadcast.spv
vulkpy/shader/div_scalar.spv
vulkpy/shader/exp.spv
vulkpy/shader/exp2.spv
vulkpy/shader/gather.spv
vulkpy/shader/gather_axis.spv
vulkpy/shader/iabs.spv
vulkpy/shader/iacos.spv
vulkpy/shader/iacosh.spv
vulkpy/shader/iadd.spv
vulkpy/shader/iadd_broadcast.spv
vulkpy/shader/iadd_scalar.spv
vulkpy/shader/iasin.spv
vulkpy/shader/iasinh.spv
vulkpy/shader/iatan.spv
vulkpy/shader/iatanh.spv
vulkpy/shader/iclamp.spv
vulkpy/shader/iclamp_ss.spv
vulkpy/shader/iclamp_sv.spv
vulkpy/shader/iclamp_vs.spv
vulkpy/shader/icos.spv
vulkpy/shader/icosh.spv
vulkpy/shader/idiv.spv
vulkpy/shader/idiv_broadcast.spv
vulkpy/shader/idiv_scalar.spv
vulkpy/shader/iexp.spv
vulkpy/shader/iexp2.spv
vulkpy/shader/iinvsqrt.spv
vulkpy/shader/ilog.spv
vulkpy/shader/ilog2.spv
vulkpy/shader/imax.spv
vulkpy/shader/imax_broadcast.spv
vulkpy/shader/imax_scalar.spv
vulkpy/shader/imin.spv
vulkpy/shader/imin_broadcast.spv
vulkpy/shader/imin_scalar.spv
vulkpy/shader/imul.spv
vulkpy/shader/imul_broadcast.spv
vulkpy/shader/imul_scalar.spv
vulkpy/shader/invsqrt.spv
vulkpy/shader/ipow.spv
vulkpy/shader/ipow_broadcast.spv
vulkpy/shader/ipow_scalar.spv
