Metadata-Version: 2.1
Name: vulkpy
Version: 0.0.7
Summary: GPGPU array on Vulkan
Home-page: https://github.com/ymd-h/vulkpy
Author: H. Yamada
Classifier: Development Status :: 4 - Beta
Classifier: Environment :: GPU
Classifier: License :: OSI Approved :: MIT License
Classifier: Programming Language :: Python :: 3 :: Only
Classifier: Programming Language :: Python :: Implementation :: CPython
Classifier: Topic :: Scientific/Engineering :: Artificial Intelligence
Provides-Extra: test
Provides-Extra: doc
License-File: LICENSE
